[
{"ContributionAdded":{"id":"root.GET","key":"purpose","value":"Get all options","eventContext":{"clientId":"anonymous","clientSessionId":"757dedd5-b2a5-454c-8c24-8ab75de13794","clientCommandBatchId":"acd25c89-b916-4f5d-b0f0-72eb5e6425ef","createdAt":"2020-09-08T17:05:15.255Z"}}}
,{"ContributionAdded":{"id":"root.GET","key":"purpose","value":"Gets all files","eventContext":{"clientId":"anonymous","clientSessionId":"963cd97e-2953-4e35-9f47-196b5f15bf31","clientCommandBatchId":"9b33dc3b-f847-499b-81b5-079897c35c1b","createdAt":"2020-09-08T17:05:34.408Z"}}}
,{"PathComponentAdded":{"pathId":"path_aMbgMSrX4j","parentPathId":"root","name":".optic","eventContext":{"clientId":"anonymous","clientSessionId":"9c90c9c8-4111-4c53-b287-028e045ddb07","clientCommandBatchId":"766b7519-a2eb-4858-a244-ac35d126eecb","createdAt":"2020-09-08T17:30:36.169Z"}}}
,{"PathComponentAdded":{"pathId":"path_GZprtp0gKK","parentPathId":"path_aMbgMSrX4j","name":"captures","eventContext":{"clientId":"anonymous","clientSessionId":"9c90c9c8-4111-4c53-b287-028e045ddb07","clientCommandBatchId":"766b7519-a2eb-4858-a244-ac35d126eecb","createdAt":"2020-09-08T17:30:36.173Z"}}}
,{"PathParameterAdded":{"pathId":"path_SK7tKyz2L7","parentPathId":"path_GZprtp0gKK","name":"capture_id","eventContext":null}}
,{"ShapeAdded":{"shapeId":"shape_Lt3WtgAWVp","baseShapeId":"$string","parameters":{"DynamicParameterList":{"shapeParameterIds":[]}},"name":"","eventContext":null}}
,{"PathParameterShapeSet":{"pathId":"path_SK7tKyz2L7","shapeDescriptor":{"shapeId":"shape_Lt3WtgAWVp","isRemoved":false},"eventContext":null}}
,{"ContributionAdded":{"id":"path_SK7tKyz2L7.GET","key":"purpose","value":"get capture by id","eventContext":{"clientId":"anonymous","clientSessionId":"9c90c9c8-4111-4c53-b287-028e045ddb07","clientCommandBatchId":"766b7519-a2eb-4858-a244-ac35d126eecb","createdAt":"2020-09-08T17:30:36.176Z"}}}
,{"BatchCommitStarted":{"batchId":"63ee501a-dabb-4375-8a76-164b1764ba18","commitMessage":"\n\nChanges:\n- Added Request with No Body\n- Added '200' Response with 'text/html' Content-Type ","eventContext":{"clientId":"anonymous","clientSessionId":"9c90c9c8-4111-4c53-b287-028e045ddb07","clientCommandBatchId":"19220af8-76ce-457d-b82a-2cf638be14f2","createdAt":"2020-09-08T17:30:47.657Z"}}}
,{"RequestParameterAddedByPathAndMethod":{"parameterId":"request-parameter_jYqD2VF5RN","pathId":"path_SK7tKyz2L7","httpMethod":"GET","parameterLocation":"query","name":"queryString","eventContext":{"clientId":"anonymous","clientSessionId":"9c90c9c8-4111-4c53-b287-028e045ddb07","clientCommandBatchId":"ffa0ded9-bb39-40db-b9ba-8216c96dfdd0","createdAt":"2020-09-08T17:30:47.658Z"}}}
,{"ShapeAdded":{"shapeId":"shape_rP39aJSjbA","baseShapeId":"$object","parameters":{"DynamicParameterList":{"shapeParameterIds":[]}},"name":"","eventContext":{"clientId":"anonymous","clientSessionId":"9c90c9c8-4111-4c53-b287-028e045ddb07","clientCommandBatchId":"ffa0ded9-bb39-40db-b9ba-8216c96dfdd0","createdAt":"2020-09-08T17:30:47.658Z"}}}
,{"RequestParameterShapeSet":{"parameterId":"request-parameter_jYqD2VF5RN","parameterDescriptor":{"shapeId":"shape_rP39aJSjbA","isRemoved":false},"eventContext":{"clientId":"anonymous","clientSessionId":"9c90c9c8-4111-4c53-b287-028e045ddb07","clientCommandBatchId":"ffa0ded9-bb39-40db-b9ba-8216c96dfdd0","createdAt":"2020-09-08T17:30:47.658Z"}}}
,{"RequestAdded":{"requestId":"request_nJuC53ouIG","pathId":"path_SK7tKyz2L7","httpMethod":"GET","eventContext":{"clientId":"anonymous","clientSessionId":"9c90c9c8-4111-4c53-b287-028e045ddb07","clientCommandBatchId":"ffa0ded9-bb39-40db-b9ba-8216c96dfdd0","createdAt":"2020-09-08T17:30:47.658Z"}}}
,{"ResponseAddedByPathAndMethod":{"responseId":"response_K92Y56J8En","pathId":"path_SK7tKyz2L7","httpMethod":"GET","httpStatusCode":200,"eventContext":{"clientId":"anonymous","clientSessionId":"9c90c9c8-4111-4c53-b287-028e045ddb07","clientCommandBatchId":"0d21245c-efda-44c5-be01-bc0fdf9b6c05","createdAt":"2020-09-08T17:30:47.661Z"}}}
,{"ShapeAdded":{"shapeId":"shape_YI8BWUovMA","baseShapeId":"$object","parameters":{"DynamicParameterList":{"shapeParameterIds":[]}},"name":"","eventContext":{"clientId":"anonymous","clientSessionId":"9c90c9c8-4111-4c53-b287-028e045ddb07","clientCommandBatchId":"0d21245c-efda-44c5-be01-bc0fdf9b6c05","createdAt":"2020-09-08T17:30:47.662Z"}}}
,{"ShapeAdded":{"shapeId":"shape_oqXmcSizGy","baseShapeId":"$string","parameters":{"DynamicParameterList":{"shapeParameterIds":[]}},"name":"","eventContext":{"clientId":"anonymous","clientSessionId":"9c90c9c8-4111-4c53-b287-028e045ddb07","clientCommandBatchId":"0d21245c-efda-44c5-be01-bc0fdf9b6c05","createdAt":"2020-09-08T17:30:47.663Z"}}}
,{"FieldAdded":{"fieldId":"field_bwpjI87ckZ","shapeId":"shape_YI8BWUovMA","name":"<!DOCTYPE HTML PUBLIC \"-//W3C//DTD HTML 4.01//EN\" \"http://www.w3.org/TR/html4/strict.dtd\">\n<html>\n<head>\n<meta http-equiv","shapeDescriptor":{"FieldShapeFromShape":{"fieldId":"field_bwpjI87ckZ","shapeId":"shape_oqXmcSizGy"}},"eventContext":{"clientId":"anonymous","clientSessionId":"9c90c9c8-4111-4c53-b287-028e045ddb07","clientCommandBatchId":"0d21245c-efda-44c5-be01-bc0fdf9b6c05","createdAt":"2020-09-08T17:30:47.664Z"}}}
,{"ResponseBodySet":{"responseId":"response_K92Y56J8En","bodyDescriptor":{"httpContentType":"text/html","shapeId":"shape_YI8BWUovMA","isRemoved":false},"eventContext":{"clientId":"anonymous","clientSessionId":"9c90c9c8-4111-4c53-b287-028e045ddb07","clientCommandBatchId":"0d21245c-efda-44c5-be01-bc0fdf9b6c05","createdAt":"2020-09-08T17:30:47.665Z"}}}
,{"BatchCommitEnded":{"batchId":"63ee501a-dabb-4375-8a76-164b1764ba18","eventContext":{"clientId":"anonymous","clientSessionId":"9c90c9c8-4111-4c53-b287-028e045ddb07","clientCommandBatchId":"edd8c395-86a3-49b2-bfb4-0352520ffc8d","createdAt":"2020-09-08T17:30:47.666Z"}}}
]